Metadata-Version: 1.0
Name: kavya-distributions
Version: 0.1
Summary: Gaussian distributions practice upload 2
Home-page: UNKNOWN
Author: kavya
Author-email: k.kavya101@gmail.com
License: UNKNOWN
Platform: UNKNOWN
